cie_restore/.gitignore
cie_restore/__init__.py
cie_restore/all.py
cie_restore/db.py
cie_restore/download.py
cie_restore/fs.py
cie_restore/posthook.sql
cie_restore/util.py
cie_restore-0.6.0.dist-info/METADATA
cie_restore-0.6.0.dist-info/WHEEL
cie_restore-0.6.0.dist-info/entry_points.txt
cie_restore-0.6.0.dist-info/RECORD
