Metadata-Version: 2.1
Name: cie-restore
Version: 0.6.0
Summary: 
Home-page: https://gitlab.com/coopiteasy/cie-restore
License: AGPL-3.0-or-later
Author: Carmen Bianca BAKKER
Author-email: carmen@coopiteasy.be
Maintainer: Coop IT Easy SC
Requires-Python: >=3.8
Classifier: License :: OSI Approved :: GNU Affero General Public License v3 or later (AGPLv3+)
Classifier: Programming Language :: Python :: 3
Classifier: Programming Language :: Python :: 3.8
Classifier: Programming Language :: Python :: 3.9
Classifier: Programming Language :: Python :: 3.10
Classifier: Programming Language :: Python :: 3.11
Classifier: Programming Language :: Python :: 3.12
Classifier: Programming Language :: Python :: 3.13
Project-URL: Repository, https://gitlab.com/coopiteasy/cie-restore
